outline_vpn/__init__.py
outline_vpn/exceptions.py
outline_vpn/outline_vpn.py
outline_vpn/structs.py
outline_vpn/utils.py
outline_vpn_api_async-0.1.2.dist-info/LICENSE.txt
outline_vpn_api_async-0.1.2.dist-info/METADATA
outline_vpn_api_async-0.1.2.dist-info/WHEEL
outline_vpn_api_async-0.1.2.dist-info/top_level.txt
outline_vpn_api_async-0.1.2.dist-info/RECORD
