Metadata-Version: 2.1
Name: outline-vpn-api-async
Version: 0.1.2
Summary: Async Python API wrapper for Outline VPN
Home-page: https://github.com/dogekiller21/outline-vpn-api-async
Author: Maxim (dogekiller21) Polyakov
Author-email: dogekiller21@gmail.com
License: MIT
License-File: LICENSE.txt
Requires-Dist: aiohttp
